README.md
setup.py
energytoolbox/__init__.py
energytoolbox/flow_case_maker.py
energytoolbox/tab_file_parser.py
energytoolbox/util.py
energytoolbox/wakeblaster_dependencies.py
energytoolbox/wakeblaster_simulation.py
energytoolbox/wind_frequency_matrix.py
energytoolbox/yield_calculator.py
wakeblaster_sdk.egg-info/PKG-INFO
wakeblaster_sdk.egg-info/SOURCES.txt
wakeblaster_sdk.egg-info/dependency_links.txt
wakeblaster_sdk.egg-info/entry_points.txt
wakeblaster_sdk.egg-info/requires.txt
wakeblaster_sdk.egg-info/top_level.txt
wakeblasterexamples/__init__.py
wakeblasterexamples/example.py
wakeblasterexamples/examples/Lillgrund.json
wakeblasterexamples/examples/SWT-2.3-93m.wtg
wakeblasterexamples/examples/flow-plane.h5
wakeblasterexamples/examples/simulator-config.json
wakeblastersdk/__init__.py
wakeblastersdk/__version__.py
wakeblastersdk/flow_plane_plots.py
wakeblastersdk/sdk.py
wakeblastersdk/emd/__init__.py
wakeblastersdk/emd/converters.py
wakeblastersdk/emd/submit.py
wakeblastersdk/emd/wakeRequest.py
wakeblastersdk/emd/wakeResult.py