Metadata-Version: 2.1
Name: wakeblaster-sdk
Version: 2.7.35
Summary: The WakeBlaster SDK
Home-page: http://www.wakeblaster.net
Author: ProPlanEn GmbH
Author-email: wakeblaster@proplanen.net
Keywords: wakeblaster windfarm modelling simulation
Classifier: Development Status :: 4 - Beta
Classifier: Intended Audience :: Developers
Classifier: Topic :: Scientific/Engineering :: Physics
Classifier: Programming Language :: Python :: 3.3
Classifier: Programming Language :: Python :: 3.4
Classifier: Programming Language :: Python :: 3.5
Requires-Python: ==3.*
